HISTORY.txt
MANIFEST.in
README.txt
setup.cfg
setup.py
repoze/__init__.py
repoze.bfg.restrequest.egg-info/PKG-INFO
repoze.bfg.restrequest.egg-info/SOURCES.txt
repoze.bfg.restrequest.egg-info/dependency_links.txt
repoze.bfg.restrequest.egg-info/entry_points.txt
repoze.bfg.restrequest.egg-info/namespace_packages.txt
repoze.bfg.restrequest.egg-info/not-zip-safe
repoze.bfg.restrequest.egg-info/paster_plugins.txt
repoze.bfg.restrequest.egg-info/requires.txt
repoze.bfg.restrequest.egg-info/top_level.txt
repoze/bfg/__init__.py
repoze/bfg/restrequest/__init__.py
repoze/bfg/restrequest/event.py
repoze/bfg/restrequest/interfaces.py