Metadata-Version: 1.0
Name: repoze.bfg.restrequest
Version: 1.0.1
Summary: a REST aware Request for implementing RESTful applications with repoze.bfg
Home-page: UNKNOWN
Author: Christian Scholz
Author-email: cs@comlounge.net
License: Repoze (BSD-like) license, http://repoze.org/license.html
Keywords: rest restful repoze bfg web development framework request wsgi
Platform: UNKNOWN
Classifier: Programming Language :: Python
Classifier: Topic :: Software Development :: Libraries :: Python Modules
Classifier: Topic :: Internet :: WWW/HTTP :: WSGI
Classifier: Topic :: Internet :: WWW/HTTP :: WSGI :: Application
Classifier: Development Status :: 5 - Production/Stable
Classifier: Environment :: Web Environment
Classifier: Intended Audience :: Developers
Classifier: Operating System :: OS Independent
Classifier: Topic :: Internet :: WWW/HTTP
